{
	"kind": "Listing",
	"data": {
		"modhash": "qaw0ecfec45330ed611af47ab14ab317a763a2722d8a94e4f3",
		"dist": null,
		"children": [{
				"kind": "LiveUpdate",
				"data": {
					"body": "8,118,667",
					"name": "LiveUpdate_4a5d0ea4-7e0b-11e8-b9ee-0ef1d5f26e28",
					"mobile_embeds": [],
					"author": "VitaminB16",
					"embeds": [],
					"created": 1530573559.0,
					"created_utc": 1530544759.0,
					"body_html": "&lt;div class=\"md\"&gt;&lt;p&gt;8,118,667&lt;/p&gt;\n&lt;/div&gt;",
					"stricken": false,
					"id": "4a5d0ea4-7e0b-11e8-b9ee-0ef1d5f26e28"
				}
			}, {
				"kind": "LiveUpdate",
				"data": {
					"body": "8,118,666",
					"name": "LiveUpdate_4938dfa8-7e0b-11e8-8613-0e770e70db4c",
					"mobile_embeds": [],
					"author": "dominodan123",
					"embeds": [],
					"created": 1530573557.0,
					"created_utc": 1530544757.0,
					"body_html": "&lt;div class=\"md\"&gt;&lt;p&gt;8,118,666&lt;/p&gt;\n&lt;/div&gt;",
					"stricken": false,
					"id": "4938dfa8-7e0b-11e8-8613-0e770e70db4c"
				}
			}, {
				"kind": "LiveUpdate",
				"data": {
					"body": "8,118,665",
					"name": "LiveUpdate_14bf23ea-7e0b-11e8-8b3f-0ef9558d4f06",
					"mobile_embeds": [],
					"author": "VitaminB16",
					"embeds": [],
					"created": 1530573469.0,
					"created_utc": 1530544669.0,
					"body_html": "&lt;div class=\"md\"&gt;&lt;p&gt;8,118,665&lt;/p&gt;\n&lt;/div&gt;",
					"stricken": false,
					"id": "14bf23ea-7e0b-11e8-8b3f-0ef9558d4f06"
				}
			}, {
				"kind": "LiveUpdate",
				"data": {
					"body": "8,118,664 not explicitly disallowed if there's no other counts after it but please don't delete valid counts",
					"name": "LiveUpdate_0213473a-7e0b-11e8-a053-0e763f31a276",
					"mobile_embeds": [],
					"author": "dominodan123",
					"embeds": [],
					"created": 1530573437.0,
					"created_utc": 1530544637.0,
					"body_html": "&lt;div class=\"md\"&gt;&lt;p&gt;8,118,664 not explicitly disallowed if there&amp;#39;s no other counts after it but please don&amp;#39;t delete valid counts&lt;/p&gt;\n&lt;/div&gt;",
					"stricken": false,
					"id": "0213473a-7e0b-11e8-a053-0e763f31a276"
				}
			}, {
				"kind": "LiveUpdate",
				"data": {
					"body": "8,118,663 yup",
					"name": "LiveUpdate_5056c1fc-7e0a-11e8-b8b1-0e9bdb58a998",
					"mobile_embeds": [],
					"author": "VitaminB16",
					"embeds": [],
					"created": 1530573139.0,
					"created_utc": 1530544339.0,
					"body_html": "&lt;div class=\"md\"&gt;&lt;p&gt;8,118,663 yup&lt;/p&gt;\n&lt;/div&gt;",
					"stricken": false,
					"id": "5056c1fc-7e0a-11e8-b8b1-0e9bdb58a998"
				}
			}, {
				"kind": "LiveUpdate",
				"data": {
					"body": "8,118,662 did you just delete your valid 661 to do that? ",
					"name": "LiveUpdate_0ad8fb36-7e0a-11e8-ba28-0ed4c680b4d8",
					"mobile_embeds": [],
					"author": "dominodan123",
					"embeds": [],
					"created": 1530573023.0,
					"created_utc": 1530544223.0,
					"body_html": "&lt;div class=\"md\"&gt;&lt;p&gt;8,118,662 did you just delete your valid 661 to do that? &lt;/p&gt;\n&lt;/div&gt;",
					"stricken": false,
					"id": "0ad8fb36-7e0a-11e8-ba28-0ed4c680b4d8"
				}
			}, {
				"kind": "LiveUpdate",
				"data": {
					"body": "8,118,661 nine minute main thread human bar",
					"name": "LiveUpdate_fece1bbe-7e09-11e8-bac4-0ed8aa831964",
					"mobile_embeds": [],
					"author": "VitaminB16",
					"embeds": [],
					"created": 1530573002.0,
					"created_utc": 1530544202.0,
					"body_html": "&lt;div class=\"md\"&gt;&lt;p&gt;8,118,661 nine minute main thread human bar&lt;/p&gt;\n&lt;/div&gt;",
					"stricken": false,
					"id": "fece1bbe-7e09-11e8-bac4-0ed8aa831964"
				}
			}, {
				"kind": "LiveUpdate",
				"data": {
					"body": "8,118,660",
					"name": "LiveUpdate_410ed9bc-7e07-11e8-83c3-0e28d216006c",
					"mobile_embeds": [],
					"author": "LeinadSpoon",
					"embeds": [],
					"created": 1530571825.0,
					"created_utc": 1530543025.0,
					"body_html": "&lt;div class=\"md\"&gt;&lt;p&gt;8,118,660&lt;/p&gt;\n&lt;/div&gt;",
					"stricken": false,
					"id": "410ed9bc-7e07-11e8-83c3-0e28d216006c"
				}
			}, {
				"kind": "LiveUpdate",
				"data": {
					"body": "8118659",
					"name": "LiveUpdate_2683ce22-7e07-11e8-bcbf-0e09ab33f73c",
					"mobile_embeds": [],
					"author": "Removedpixel",
					"embeds": [],
					"created": 1530571781.0,
					"created_utc": 1530542981.0,
					"body_html": "&lt;div class=\"md\"&gt;&lt;p&gt;8118659&lt;/p&gt;\n&lt;/div&gt;",
					"stricken": false,
					"id": "2683ce22-7e07-11e8-bcbf-0e09ab33f73c"
				}
			}, {
				"kind": "LiveUpdate",
				"data": {
					"body": "8,118,658",
					"name": "LiveUpdate_189ea47c-7e06-11e8-8008-0e53bf8edc48",
					"mobile_embeds": [],
					"author": "LeinadSpoon",
					"embeds": [],
					"created": 1530571328.0,
					"created_utc": 1530542528.0,
					"body_html": "&lt;div class=\"md\"&gt;&lt;p&gt;8,118,658&lt;/p&gt;\n&lt;/div&gt;",
					"stricken": false,
					"id": "189ea47c-7e06-11e8-8008-0e53bf8edc48"
				}
			}, {
				"kind": "LiveUpdate",
				"data": {
					"body": "8,118,657",
					"name": "LiveUpdate_338d455a-7e05-11e8-8080-0eb0e9e7e040",
					"mobile_embeds": [],
					"author": "artbn",
					"embeds": [],
					"created": 1530570943.0,
					"created_utc": 1530542143.0,
					"body_html": "&lt;div class=\"md\"&gt;&lt;p&gt;8,118,657&lt;/p&gt;\n&lt;/div&gt;",
					"stricken": false,
					"id": "338d455a-7e05-11e8-8080-0eb0e9e7e040"
				}
			}, {
				"kind": "LiveUpdate",
				"data": {
					"body": "8,118,656 ",
					"name": "LiveUpdate_50f1ef02-7e04-11e8-b270-0ea5086a5d36",
					"mobile_embeds": [],
					"author": "LeinadSpoon",
					"embeds": [],
					"created": 1530570563.0,
					"created_utc": 1530541763.0,
					"body_html": "&lt;div class=\"md\"&gt;&lt;p&gt;8,118,656 &lt;/p&gt;\n&lt;/div&gt;",
					"stricken": false,
					"id": "50f1ef02-7e04-11e8-b270-0ea5086a5d36"
				}
			}, {
				"kind": "LiveUpdate",
				"data": {
					"body": "8118655",
					"name": "LiveUpdate_4b66c2f6-7e04-11e8-a90c-0ea13bf87e80",
					"mobile_embeds": [],
					"author": "dominodan123",
					"embeds": [],
					"created": 1530570554.0,
					"created_utc": 1530541754.0,
					"body_html": "&lt;div class=\"md\"&gt;&lt;p&gt;8118655&lt;/p&gt;\n&lt;/div&gt;",
					"stricken": false,
					"id": "4b66c2f6-7e04-11e8-a90c-0ea13bf87e80"
				}
			}, {
				"kind": "LiveUpdate",
				"data": {
					"body": "8,118,654",
					"name": "LiveUpdate_9c4c741a-7e02-11e8-8564-0e1a1df1b1d0",
					"mobile_embeds": [],
					"author": "LeinadSpoon",
					"embeds": [],
					"created": 1530569831.0,
					"created_utc": 1530541031.0,
					"body_html": "&lt;div class=\"md\"&gt;&lt;p&gt;8,118,654&lt;/p&gt;\n&lt;/div&gt;",
					"stricken": false,
					"id": "9c4c741a-7e02-11e8-8564-0e1a1df1b1d0"
				}
			}, {
				"kind": "LiveUpdate",
				"data": {
					"body": "8,118,653",
					"name": "LiveUpdate_6e7c9a10-7e02-11e8-9fd3-0edbbe2223ea",
					"mobile_embeds": [],
					"author": "smarvin6689",
					"embeds": [],
					"created": 1530569754.0,
					"created_utc": 1530540954.0,
					"body_html": "&lt;div class=\"md\"&gt;&lt;p&gt;8,118,653&lt;/p&gt;\n&lt;/div&gt;",
					"stricken": false,
					"id": "6e7c9a10-7e02-11e8-9fd3-0edbbe2223ea"
				}
			}, {
				"kind": "LiveUpdate",
				"data": {
					"body": "8,118,652",
					"name": "LiveUpdate_f112a8ea-7e00-11e8-801d-0e3895e4df2c",
					"mobile_embeds": [],
					"author": "LeinadSpoon",
					"embeds": [],
					"created": 1530569114.0,
					"created_utc": 1530540314.0,
					"body_html": "&lt;div class=\"md\"&gt;&lt;p&gt;8,118,652&lt;/p&gt;\n&lt;/div&gt;",
					"stricken": false,
					"id": "f112a8ea-7e00-11e8-801d-0e3895e4df2c"
				}
			}, {
				"kind": "LiveUpdate",
				"data": {
					"body": "8,118,651",
					"name": "LiveUpdate_a59bc140-7dff-11e8-8685-0ef0e5d9fc48",
					"mobile_embeds": [],
					"author": "artbn",
					"embeds": [],
					"created": 1530568558.0,
					"created_utc": 1530539758.0,
					"body_html": "&lt;div class=\"md\"&gt;&lt;p&gt;8,118,651&lt;/p&gt;\n&lt;/div&gt;",
					"stricken": false,
					"id": "a59bc140-7dff-11e8-8685-0ef0e5d9fc48"
				}
			}, {
				"kind": "LiveUpdate",
				"data": {
					"body": "8,118,650 Good morning!",
					"name": "LiveUpdate_f5485f72-7df6-11e8-9b74-0e53bf8edc48",
					"mobile_embeds": [],
					"author": "LeinadSpoon",
					"embeds": [],
					"created": 1530564826.0,
					"created_utc": 1530536026.0,
					"body_html": "&lt;div class=\"md\"&gt;&lt;p&gt;8,118,650 Good morning!&lt;/p&gt;\n&lt;/div&gt;",
					"stricken": false,
					"id": "f5485f72-7df6-11e8-9b74-0e53bf8edc48"
				}
			}, {
				"kind": "LiveUpdate",
				"data": {
					"body": "8,118,649",
					"name": "LiveUpdate_e925331e-7df6-11e8-87dd-0ea5af423f1a",
					"mobile_embeds": [],
					"author": "isaacbarron02",
					"embeds": [],
					"created": 1530564806.0,
					"created_utc": 1530536006.0,
					"body_html": "&lt;div class=\"md\"&gt;&lt;p&gt;8,118,649&lt;/p&gt;\n&lt;/div&gt;",
					"stricken": false,
					"id": "e925331e-7df6-11e8-87dd-0ea5af423f1a"
				}
			}, {
				"kind": "LiveUpdate",
				"data": {
					"body": "8,118,648",
					"name": "LiveUpdate_115f29a4-7df5-11e8-9124-0e9d53818628",
					"mobile_embeds": [],
					"author": "LeinadSpoon",
					"embeds": [],
					"created": 1530564014.0,
					"created_utc": 1530535214.0,
					"body_html": "&lt;div class=\"md\"&gt;&lt;p&gt;8,118,648&lt;/p&gt;\n&lt;/div&gt;",
					"stricken": false,
					"id": "115f29a4-7df5-11e8-9124-0e9d53818628"
				}
			}, {
				"kind": "LiveUpdate",
				"data": {
					"body": "8 118 647 thanks",
					"name": "LiveUpdate_3e0dcff8-7ded-11e8-8e79-0e677b4e7e60",
					"mobile_embeds": [],
					"author": "Majestic_Bear",
					"embeds": [],
					"created": 1530560653.0,
					"created_utc": 1530531853.0,
					"body_html": "&lt;div class=\"md\"&gt;&lt;p&gt;8 118 647 thanks&lt;/p&gt;\n&lt;/div&gt;",
					"stricken": false,
					"id": "3e0dcff8-7ded-11e8-8e79-0e677b4e7e60"
				}
			}, {
				"kind": "LiveUpdate",
				"data": {
					"body": "8118646",
					"name": "LiveUpdate_ec883f92-7dec-11e8-abc9-0e376ed12720",
					"mobile_embeds": [],
					"author": "MrBahr12",
					"embeds": [],
					"created": 1530560516.0,
					"created_utc": 1530531716.0,
					"body_html": "&lt;div class=\"md\"&gt;&lt;p&gt;8118646&lt;/p&gt;\n&lt;/div&gt;",
					"stricken": false,
					"id": "ec883f92-7dec-11e8-abc9-0e376ed12720"
				}
			}, {
				"kind": "LiveUpdate",
				"data": {
					"body": "if anyone is here, requesting a count in slow count",
					"name": "LiveUpdate_215837f0-7dec-11e8-ab2b-0e011879111e",
					"mobile_embeds": [],
					"author": "Majestic_Bear",
					"embeds": [],
					"created": 1530560175.0,
					"created_utc": 1530531375.0,
					"body_html": "&lt;div class=\"md\"&gt;&lt;p&gt;if anyone is here, requesting a count in slow count&lt;/p&gt;\n&lt;/div&gt;",
					"stricken": false,
					"id": "215837f0-7dec-11e8-ab2b-0e011879111e"
				}
			}, {
				"kind": "LiveUpdate",
				"data": {
					"body": "8 118 645",
					"name": "LiveUpdate_fabfff42-7deb-11e8-ba1b-0e69db7837b8",
					"mobile_embeds": [],
					"author": "Majestic_Bear",
					"embeds": [],
					"created": 1530560111.0,
					"created_utc": 1530531311.0,
					"body_html": "&lt;div class=\"md\"&gt;&lt;p&gt;8 118 645&lt;/p&gt;\n&lt;/div&gt;",
					"stricken": false,
					"id": "fabfff42-7deb-11e8-ba1b-0e69db7837b8"
				}
			}, {
				"kind": "LiveUpdate",
				"data": {
					"body": "8118644",
					"name": "LiveUpdate_1f6e4c66-7de9-11e8-80eb-0e011879111e",
					"mobile_embeds": [],
					"author": "LeinadSpoon",
					"embeds": [],
					"created": 1530558884.0,
					"created_utc": 1530530084.0,
					"body_html": "&lt;div class=\"md\"&gt;&lt;p&gt;8118644&lt;/p&gt;\n&lt;/div&gt;",
					"stricken": false,
					"id": "1f6e4c66-7de9-11e8-80eb-0e011879111e"
				}
			}
		],
		"after": "LiveUpdate_1f6e4c66-7de9-11e8-80eb-0e011879111e",
		"before": null
	}
}
